ffmpy.py
py.typed
ffmpy-0.3.3.dist-info/LICENSE
ffmpy-0.3.3.dist-info/METADATA
ffmpy-0.3.3.dist-info/WHEEL
ffmpy-0.3.3.dist-info/RECORD
