Metadata-Version: 2.1
Name: ffmpy
Version: 0.3.3
Summary: A simple Python wrapper for FFmpeg
Home-page: https://github.com/Ch00k/ffmpy
License: MIT
Keywords: ffmpeg,ffprobe,ffplay,ffserver,wrapper,media,audio,video,transcoding
Author: Andrii Yurchuk
Author-email: ay@mntw.re
Requires-Python: >=3.8.1,<4.0.0
Classifier: Development Status :: 4 - Beta
Classifier: Intended Audience :: Developers
Classifier: License :: OSI Approved :: MIT License
Classifier: Natural Language :: English
Classifier: Operating System :: MacOS :: MacOS X
Classifier: Operating System :: Microsoft :: Windows
Classifier: Operating System :: POSIX
Classifier: Operating System :: POSIX :: BSD
Classifier: Operating System :: POSIX :: Linux
Classifier: Programming Language :: Python :: 3
Classifier: Programming Language :: Python :: 3.9
Classifier: Programming Language :: Python :: 3.10
Classifier: Programming Language :: Python :: 3.11
Classifier: Programming Language :: Python :: 3.12
Classifier: Programming Language :: Python :: 3.8
Classifier: Programming Language :: Python :: Implementation :: CPython
Classifier: Programming Language :: Python :: Implementation :: PyPy
Classifier: Topic :: Multimedia :: Sound/Audio
Project-URL: Documentation, https://ffmpy.readthedocs.io
Project-URL: Repository, https://github.com/Ch00k/ffmpy
